LICENSE.txt
README.md
setup.py
bopt_slf/__init__.py
bopt_slf.egg-info/PKG-INFO
bopt_slf.egg-info/SOURCES.txt
bopt_slf.egg-info/dependency_links.txt
bopt_slf.egg-info/requires.txt
bopt_slf.egg-info/top_level.txt
bopt_slf/core/__init__.py
bopt_slf/core/main.py
bopt_slf/utils/Acq_fun.py
bopt_slf/utils/Aux.py
bopt_slf/utils/Initialize.py
bopt_slf/utils/Models.py
bopt_slf/utils/Plotting.py
bopt_slf/utils/Preprocessing_data.py
bopt_slf/utils/Querry_points.py
bopt_slf/utils/Superlevel_set_filtration.py
bopt_slf/utils/Update.py
bopt_slf/utils/__init__.py