Metadata-Version: 2.1
Name: bopt-slf
Version: 1.0.4
Summary: Bayesian optimization for constrained or unconstrained, continuous, discrete or mixed data problems
Author: Javier Morlet-Espinosa
Author-email: a00833961@tec.mx
License-File: LICENSE.txt
Requires-Dist: numpy>=1.23.5
Requires-Dist: sympy>=1.11.1
Requires-Dist: pandas>=2.0.3
Requires-Dist: GPy>=1.10.0
Requires-Dist: scipy>=1.10.1
Requires-Dist: scikit-learn>=1.1.3
Requires-Dist: properscoring>=0.1
Requires-Dist: prince>=0.12.1
Requires-Dist: matplotlib>=3.7.3
